pybharphonetic/__init__.py
pybharphonetic/bharphonetic.py
pybharphonetic/config.py
pybharphonetic/resources/__init__.py
pybharphonetic/resources/avrodict_assamese.json
pybharphonetic/resources/avrodict_bengali.json
pybharphonetic/resources/avrodict_bengali_reverse.json
pybharphonetic/resources/avrodict_bodo.json
pybharphonetic/resources/avrodict_dogri.json
pybharphonetic/resources/avrodict_gujrati.json
pybharphonetic/resources/avrodict_hindi.json
pybharphonetic/resources/avrodict_hindi_reverse.json
pybharphonetic/resources/avrodict_kannada.json
pybharphonetic/resources/avrodict_kashmiri.json
pybharphonetic/resources/avrodict_konkani.json
pybharphonetic/resources/avrodict_maithili.json
pybharphonetic/resources/avrodict_malayalam.json
pybharphonetic/resources/avrodict_manipuri.json
pybharphonetic/resources/avrodict_marathi.json
pybharphonetic/resources/avrodict_nepali.json
pybharphonetic/resources/avrodict_odia.json
pybharphonetic/resources/avrodict_punjabi.json
pybharphonetic/resources/avrodict_sanskrit.json
pybharphonetic/resources/avrodict_santhali.json
pybharphonetic/resources/avrodict_sindhi.json
pybharphonetic/resources/avrodict_tamil.json
pybharphonetic/resources/avrodict_telegu.json
pybharphonetic/resources/avrodict_telugu.json
pybharphonetic/resources/avrodict_urdu.json
pybharphonetic/utils/__init__.py
pybharphonetic/utils/count.py
pybharphonetic/utils/validate.py
pybharphonetic-1.1.dist-info/LICENSE
pybharphonetic-1.1.dist-info/METADATA
pybharphonetic-1.1.dist-info/WHEEL
pybharphonetic-1.1.dist-info/top_level.txt
pybharphonetic-1.1.dist-info/RECORD
