Metadata-Version: 2.1
Name: pybharphonetic
Version: 1.1
Summary: Python implementation to convert Indic languages to phonetic
Home-page: https://github.com/PA-Games-SSDDR/pybharphonetic
Author: Subrata Sarkar
Author-email: subrotosarkar32@gmail.com
License: GNU GPL v3 or later
Classifier: Development Status :: 3 - Alpha
Classifier: Intended Audience :: Developers
Classifier: License :: OSI Approved :: GNU General Public License v3 or later (GPLv3+)
Classifier: Operating System :: OS Independent
Classifier: Programming Language :: Python :: 3
License-File: LICENSE
